Workbook

Sheet Summary
A1: Budget — September 2026
A2: Blue cells are inputs. Everything else is a formula. Edit amounts on the Fixed, Variable and Savings tabs.
A4: Salary (net, monthly) | B4: 70000 | C4: Source: FNB statements 135-138, constant at R70,000
A6: Less: Fixed expenses | B6: =-Fixed!E34 -> -58542.21 | C6: =B6/$B$4 -> -0.83631729
A7: LEFT AFTER FIXED | B7: =B4+B6 -> 11457.79 | C7: =B7/$B$4 -> 0.16368271
A8: Less: Variable expenses | B8: =-Variable!E23 -> -16861.18 | C8: =B8/$B$4 -> -0.240874
A9: LEFT AFTER FIXED + VARIABLE | B9: =B7+B8 -> -5403.39 | C9: =B9/$B$4 -> -0.077191286
A10: Less: Savings instructions | B10: =-Savings!E9 -> -14506.22 | C10: =B10/$B$4 -> -0.20723171
A11: MONTHLY GAP | B11: =B9+B10 -> -19909.61 | C11: =B11/$B$4 -> -0.284423
A15: How the three blocks are defined
A16: Fixed — a standing instruction at a rate you cannot change this month, shown at its most recent amount rather than an average.
A17: Variable — you choose when and how much, so these are 4-cycle averages. Prepaid electricity and airtime sit here for that reason.
A18: Savings — standing instructions too, but money kept rather than spent, so they are kept in their own block.
A20: Open items
A21: Payments to a second credit account (R7,750/mo) are an average of five irregular and accelerating payments. No statement for that account exists yet.
A22: Ril Res001 (R850/mo) first appeared on 1 September and is assumed recurring.
A23: A R200,000 capital repayment on 9 September may cut the structured-loan instalment from 30 September. Watch that debit.
A24: EasyEquities TFSA at R3,006.22/mo is R74.64/yr over the R36,000 annual limit; excess contributions are taxed at 40%.
A26: Excluded: R26,060.66 of out-of-pocket medical in June — a one-off event, not a monthly cost.
A27: Source: FNB cheque statements 135-138 and card statements 130-132, all reconciled to the printed balances.

Sheet Fixed
A1: Fixed
A2: Edit the blue amounts. Annual and the Summary tab recalculate. Amounts are per month.
A4: Item | B4: Frequency | C4: Clears | D4: Account | E4: Per month | F4: Per year | G4: % of salary | H4: Basis / note
A5: DEBT | E5: =SUM(E6:E9) -> 28794.86 | F5: =E5*12 -> 345538.32 | G5: =E5/Summary!$B$4 -> 0.41135514
A6: FNB Structured Loan | B6: Monthly | C6: 31st | D6: Cheque | E6: 22202.79 | F6: =E6*12 -> 266433.48 | G6: =E6/Summary!$B$4 -> 0.31718271 | H6: RISING — Standing instruction at the September rate
A7: WesBank vehicle finance | B7: Monthly | C7: 31st | D7: Cheque | E7: 5749.6 | F7: =E7*12 -> 68995.2 | G7: =E7/Summary!$B$4 -> 0.082137143 | H7: Standing instruction at the September rate
A8: iStore budget facility instalment | B8: Monthly | C8: Statement | D8: Card 4002 | E8: 773.47 | F8: =E8*12 -> 9281.64 | G8: =E8/Summary!$B$4 -> 0.011049571 | H8: 11.50% p.a. - R9868.11 still outstanding
A9: FNB Home admin fee | B9: Monthly | C9: 31st | D9: Cheque | E9: 69 | F9: =E9*12 -> 828 | G9: =E9/Summary!$B$4 -> 0.00098571429 | H9: Standing instruction
A10: INSURANCE & COVER | E10: =SUM(E11:E15) -> 15785.84 | F10: =E10*12 -> 189430.08 | G10: =E10/Summary!$B$4 -> 0.225512
A11: Discovery premium | B11: Monthly | C11: 1st | D11: Cheque | E11: 7578 | F11: =E11*12 -> 90936 | G11: =E11/Summary!$B$4 -> 0.10825714 | H11: Medical aid - claims refunded in May and June
A12: FNB Life (Fl105Gz98) | B12: Monthly | C12: 25th | D12: Cheque | E12: 4106.61 | F12: =E12*12 -> 49279.32 | G12: =E12/Summary!$B$4 -> 0.058665857 | H12: Life and risk cover
A13: JAC insurance | B13: Monthly | C13: 1st | D13: Cheque | E13: 3836.27 | F13: =E13*12 -> 46035.24 | G13: =E13/Summary!$B$4 -> 0.054803857 | H13: Life and risk cover - confirmed by you
A14: Netstar vehicle tracking | B14: Monthly | C14: 1st | D14: Cheque | E14: 231.38 | F14: =E14*12 -> 2776.56 | G14: =E14/Summary!$B$4 -> 0.0033054286 | H14: Usually an insurer requirement
A15: FNB Life (Fl68Zw53) | B15: Monthly | C15: 1st | D15: Cheque | E15: 33.58 | F15: =E15*12 -> 402.96 | G15: =E15/Summary!$B$4 -> 0.00047971429 | H15: Second small policy
A16: SUBSCRIPTIONS | E16: =SUM(E17:E17) -> 6143.54 | F16: =E16*12 -> 73722.48 | G16: =E16/Summary!$B$4 -> 0.087764857
A17: Happy Hound | B17: Weekly | C17: Every week | D17: Card 4002 | E17: 6143.54 | F17: =E17*12 -> 73722.48 | G17: =E17/Summary!$B$4 -> 0.087764857 | H17: R1417.74 per week x 52/12 - on a dedicated card
A18: CONNECTIVITY | E18: =SUM(E19:E26) -> 5804.01 | F18: =E18*12 -> 69648.12 | G18: =E18/Summary!$B$4 -> 0.082914429
A19: RSAWEB fibre line 2 | B19: Monthly | C19: 1st | D19: Cheque | E19: 1728 | F19: =E19*12 -> 20736 | G19: =E19/Summary!$B$4 -> 0.024685714 | H19: DUPLICATE? — Second fibre line
A20: RSAWEB fibre line 1 | B20: Monthly | C20: 1st | D20: Cheque | E20: 1299.01 | F20: =E20*12 -> 15588.12 | G20: =E20/Summary!$B$4 -> 0.018557286 | H20: DUPLICATE? — First fibre line
A21: FNB Connect 8858332324 | B21: Monthly | C21: 1st | D21: Cheque | E21: 749 | F21: =E21*12 -> 8988 | G21: =E21/Summary!$B$4 -> 0.0107
A22: FNB Connect 8872638615 | B22: Monthly | C22: 25th | D22: Cheque | E22: 579 | F22: =E22*12 -> 6948 | G22: =E22/Summary!$B$4 -> 0.0082714286
A23: FNB Connect 8858332521 | B23: Monthly | C23: 1st | D23: Cheque | E23: 499 | F23: =E23*12 -> 5988 | G23: =E23/Summary!$B$4 -> 0.0071285714
A24: Hybrid Connect top-up | B24: Monthly | C24: 1st | D24: Cheque | E24: 415 | F24: =E24*12 -> 4980 | G24: =E24/Summary!$B$4 -> 0.0059285714
A25: Stratum | B25: Monthly | C25: 1st | D25: Cheque | E25: 390 | F25: =E25*12 -> 4680 | G25: =E25/Summary!$B$4 -> 0.0055714286
A26: Hybrid Connect top-up | B26: Monthly | C26: 1st | D26: Cheque | E26: 145 | F26: =E26*12 -> 1740 | G26: =E26/Summary!$B$4 -> 0.0020714286
A27: UNIDENTIFIED | E27: =SUM(E28:E28) -> 850 | F27: =E27*12 -> 10200 | G27: =E27/Summary!$B$4 -> 0.012142857
A28: Ril Res001 | B28: Monthly | C28: 1st | D28: Cheque | E28: 850 | F28: =E28*12 -> 10200 | G28: =E28/Summary!$B$4 -> 0.012142857 | H28: UNIDENTIFIED — First appeared 1 September - assumed recurring
A29: BANK CHARGES | E29: =SUM(E30:E31) -> 764.96 | F29: =E29*12 -> 9179.52 | G29: =E29/Summary!$B$4 -> 0.010928
A30: Monthly account service fee | B30: Monthly | C30: 18th | D30: Cheque | E30: 661.46 | F30: =E30*12 -> 7937.52 | G30: =E30/Summary!$B$4 -> 0.0094494286 | H30: RISING — Rose from 625.00 in July
A31: Linked account service charges | B31: Monthly | C31: 31st | D31: Cheque | E31: 103.5 | F31: =E31*12 -> 1242 | G31: =E31/Summary!$B$4 -> 0.0014785714 | H31: From account 62724872339
A32: HOME | E32: =SUM(E33:E33) -> 399 | F32: =E32*12 -> 4788 | G32: =E32/Summary!$B$4 -> 0.0057
A33: Edgekloof levy | B33: Monthly | C33: 1st | D33: Cheque | E33: 399 | F33: =E33*12 -> 4788 | G33: =E33/Summary!$B$4 -> 0.0057
A34: TOTAL FIXED | E34: =E5+E10+E16+E18+E27+E29+E32 -> 58542.21 | F34: =E34*12 -> 702506.52 | G34: =E34/Summary!$B$4 -> 0.83631729

Sheet Variable
A1: Variable
A2: Edit the blue amounts. Annual and the Summary tab recalculate. Amounts are per month.
A4: Item | B4: Frequency | C4: Clears | D4: Account | E4: Per month | F4: Per year | G4: % of salary | H4: Basis / note
A5: SECOND CREDIT ACCOUNT | E5: =SUM(E6:E6) -> 7750 | F5: =E5*12 -> 93000 | G5: =E5/Summary!$B$4 -> 0.11071429
A6: Payments to a second credit account | B6: Irregular | C6: Varies | D6: Unknown | E6: 7750 | F6: =E6*12 -> 93000 | G6: =E6/Summary!$B$4 -> 0.11071429 | H6: UNIDENTIFIED — 4-cycle average of 5 payments - accelerating
A7: FOOD | E7: =SUM(E8:E8) -> 3196.98 | F7: =E7*12 -> 38363.76 | G7: =E7/Summary!$B$4 -> 0.045671143
A8: Groceries and eating out | B8: Irregular | C8: - | D8: Both | E8: 3196.98 | F8: =E8*12 -> 38363.76 | G8: =E8/Summary!$B$4 -> 0.045671143 | H8: 4-cycle average across both accounts
A9: FAMILY | E9: =SUM(E10:E10) -> 2662.65 | F9: =E9*12 -> 31951.8 | G9: =E9/Summary!$B$4 -> 0.038037857
A10: Family support | B10: Irregular | C10: - | D10: Cheque | E10: 2662.65 | F10: =E10*12 -> 31951.8 | G10: =E10/Summary!$B$4 -> 0.038037857 | H10: 4-cycle average - PayShap and app transfers
A11: SHOPPING | E11: =SUM(E12:E12) -> 1196.61 | F11: =E11*12 -> 14359.32 | G11: =E11/Summary!$B$4 -> 0.017094429
A12: Shopping and other retail | B12: Irregular | C12: - | D12: Both | E12: 1196.61 | F12: =E12*12 -> 14359.32 | G12: =E12/Summary!$B$4 -> 0.017094429 | H12: 4-cycle average - Takealot Yuppiechef pets
A13: TRAVEL | E13: =SUM(E14:E14) -> 777.7 | F13: =E13*12 -> 9332.4 | G13: =E13/Summary!$B$4 -> 0.01111
A14: Travel and leisure | B14: Irregular | C14: - | D14: Both | E14: 777.7 | F14: =E14*12 -> 9332.4 | G14: =E14/Summary!$B$4 -> 0.01111 | H14: 4-cycle average - one weekend away
A15: HOME | E15: =SUM(E16:E16) -> 625 | F15: =E15*12 -> 7500 | G15: =E15/Summary!$B$4 -> 0.0089285714
A16: Prepaid electricity | B16: Irregular | C16: - | D16: Cheque | E16: 625 | F16: =E16*12 -> 7500 | G16: =E16/Summary!$B$4 -> 0.0089285714 | H16: 4-cycle average - you choose when and how much
A17: TRANSPORT | E17: =SUM(E18:E18) -> 344.14 | F17: =E17*12 -> 4129.68 | G17: =E17/Summary!$B$4 -> 0.0049162857
A18: Transport and fuel | B18: Irregular | C18: - | D18: Cheque | E18: 344.14 | F18: =E18*12 -> 4129.68 | G18: =E18/Summary!$B$4 -> 0.0049162857 | H18: 4-cycle average - one fuel purchase in four months
A19: CONNECTIVITY | E19: =SUM(E20:E20) -> 188.25 | F19: =E19*12 -> 2259 | G19: =E19/Summary!$B$4 -> 0.0026892857
A20: Airtime top-ups | B20: Irregular | C20: - | D20: Cheque | E20: 188.25 | F20: =E20*12 -> 2259 | G20: =E20/Summary!$B$4 -> 0.0026892857 | H20: 4-cycle average
A21: BANK CHARGES | E21: =SUM(E22:E22) -> 119.85 | F21: =E21*12 -> 1438.2 | G21: =E21/Summary!$B$4 -> 0.0017121429
A22: Overdraft and card interest | B22: Irregular | C22: - | D22: Both | E22: 119.85 | F22: =E22*12 -> 1438.2 | G22: =E22/Summary!$B$4 -> 0.0017121429 | H22: 4-cycle average
A23: TOTAL VARIABLE | E23: =E5+E7+E9+E11+E13+E15+E17+E19+E21 -> 16861.18 | F23: =E23*12 -> 202334.16 | G23: =E23/Summary!$B$4 -> 0.240874

Sheet Savings
A1: Savings
A2: Edit the blue amounts. Annual and the Summary tab recalculate. Amounts are per month.
A4: Item | B4: Frequency | C4: Clears | D4: Account | E4: Per month | F4: Per year | G4: % of salary | H4: Basis / note
A5: SAVINGS | E5: =SUM(E6:E8) -> 14506.22 | F5: =E5*12 -> 174074.64 | G5: =E5/Summary!$B$4 -> 0.20723171
A6: Scheduled transfer to savings | B6: Monthly | C6: 27th | D6: Cheque | E6: 9000 | F6: =E6*12 -> 108000 | G6: =E6/Summary!$B$4 -> 0.12857143 | H6: The flexible one - clears before month-end
A7: EasyEquities TFSA | B7: Monthly | C7: 1st | D7: Cheque | E7: 3006.22 | F7: =E7*12 -> 36074.64 | G7: =E7/Summary!$B$4 -> 0.042946 | H7: CHECK — R74.64/yr over the R36000 annual limit
A8: FNB Invest | B8: Monthly | C8: 17th | D8: Cheque | E8: 2500 | F8: =E8*12 -> 30000 | G8: =E8/Summary!$B$4 -> 0.035714286
A9: TOTAL SAVINGS | E9: =E5 -> 14506.22 | F9: =E9*12 -> 174074.64 | G9: =E9/Summary!$B$4 -> 0.20723171
